entra_scopes_finder/__init__.py
entra_scopes_finder/cli.py
entra_scopes_finder-1.0.1.dist-info/licenses/LICENSE
entra_scopes_finder-1.0.1.dist-info/METADATA
entra_scopes_finder-1.0.1.dist-info/WHEEL
entra_scopes_finder-1.0.1.dist-info/entry_points.txt
entra_scopes_finder-1.0.1.dist-info/top_level.txt
entra_scopes_finder-1.0.1.dist-info/RECORD
