Metadata-Version: 2.4
Name: entra-scopes-finder
Version: 1.0.1
Summary: A CLI tool for finding Azure first party clients with pre-consented scopes
Home-page: https://github.com/kidtronnix/azure-clients
Author: Your Name
Author-email: Stewart Maxwell <smaxwellstewart@gmail.com>
Maintainer-email: Stewart Maxwell <smaxwellstewart@gmail.com>
License: MIT License
Project-URL: Homepage, https://github.com/kidtronnix/entra-scopes-finder
Project-URL: Repository, https://github.com/kidtronnix/entra-scopes-finder
Project-URL: Issues, https://github.com/kidtronnix/entra-scopes-finder/issues
Project-URL: Documentation, https://github.com/kidtronnix/entra-scopes-finder#readme
Keywords: azure,entra,security,scopes,oauth,red-team
Classifier: Development Status :: 4 - Beta
Classifier: Intended Audience :: Developers
Classifier: Intended Audience :: System Administrators
Classifier: License :: OSI Approved :: MIT License
Classifier: Operating System :: OS Independent
Classifier: Programming Language :: Python :: 3
Classifier: Programming Language :: Python :: 3.6
Classifier: Programming Language :: Python :: 3.7
Classifier: Programming Language :: Python :: 3.8
Classifier: Programming Language :: Python :: 3.9
Classifier: Programming Language :: Python :: 3.10
Classifier: Programming Language :: Python :: 3.11
Classifier: Programming Language :: Python :: 3.12
Classifier: Topic :: Security
Classifier: Topic :: System :: Systems Administration
Classifier: Topic :: Utilities
Requires-Python: >=3.6
License-File: LICENSE
Requires-Dist: requests>=2.20.0
Dynamic: author
Dynamic: home-page
Dynamic: license-file
Dynamic: requires-python
